ai_jup/_version.py
jupyvibes-0.1.2.data/data/share/jupyter/labextensions/ai-jup/install.json
jupyvibes-0.1.2.dist-info/METADATA
jupyvibes-0.1.2.dist-info/WHEEL
jupyvibes-0.1.2.dist-info/licenses/LICENSE
jupyvibes-0.1.2.dist-info/RECORD
