Metadata-Version: 2.4
Name: jupyvibes
Version: 0.1.2
Dynamic: Keywords
Summary: JupyterLab extension for AI-powered prompt cells with variable and function references
Project-URL: Homepage, https://github.com/hamelsmu/ai-jup
Project-URL: Repository, https://github.com/hamelsmu/ai-jup.git
Author: Hamel Husain
License: MIT License
License-File: LICENSE
Classifier: Framework :: Jupyter
Classifier: Framework :: Jupyter :: JupyterLab
Classifier: Framework :: Jupyter :: JupyterLab :: 4
Classifier: Framework :: Jupyter :: JupyterLab :: Extensions
Classifier: Framework :: Jupyter :: JupyterLab :: Extensions :: Prebuilt
Classifier: License :: OSI Approved :: MIT License
Classifier: Programming Language :: Python
Classifier: Programming Language :: Python :: 3
Classifier: Programming Language :: Python :: 3.8
Classifier: Programming Language :: Python :: 3.9
Classifier: Programming Language :: Python :: 3.10
Classifier: Programming Language :: Python :: 3.11
Classifier: Programming Language :: Python :: 3.12
Requires-Python: >=3.8
Requires-Dist: fastcore>=1.7.0
Requires-Dist: jupyter-server<3,>=2.0.0
Requires-Dist: litellm>=1.40.0
Provides-Extra: test
Requires-Dist: httpx>=0.24.0; extra == 'test'
Requires-Dist: pytest-asyncio>=0.21; extra == 'test'
Requires-Dist: pytest>=7.0; extra == 'test'
Requires-Dist: websocket-client>=1.6.0; extra == 'test'
